[{
  "id": null,
  "insertUserId": 4,
  "insertUser": "Katie Wilson",
  "insertTimeUTC": 1533715328789,
  "insertTime": 1533715328789,
  "updateUserId": 15,
  "updateUser": "Config FM3",
  "updateTimeUTC": 1539177788948,
  "updateTime": 1539177788948,
  "organizationId": 2,
  "valid": true,
  "cancellationTime": null,
  "cancellationUser": null,
  "cancellationUserId": null,
  "cancellationTimeUTC": null,
  "name": "Braden",
  "code": "schedaBraden",
  "html": "<section class=\"panel\">\n\t<div class=\"panel-body\" ng-click=\"selectRadio();\">\n\t\t<div class=\"row\">\n\t\t\t<div class=\"col-sm-4 col-md-12\">\n\t\t\t\t<div class=\"form-group\">\n\t\t\t\t\t<label class=\"col-sm-12\">Commento</label>\n\t\t\t\t\t<div class=\"col-sm-12\">\n\t\t\t\t\t\t<textarea class=\"form-control\" ng-model=\"formData.informasioniGenerali.commento\" rows=\"5\"></textarea>\n\t\t\t\t\t\t<input class=\"form-control\" type=\"text\" summary=\"BRADENCommento\" ng-model=\"formData.scoreTotal\" ng-show=\"false\">\n\t\t\t\t\t</div>\n\t\t\t\t</div>\n\t\t\t</div>\n\t\t</div>\n\t\t<div class=\"row\">\n\t\t\t<div class=\"col-xs-12 col-md-12 col-lg-6\">\n\t\t\t\t<div class=\"panel panel-primary\">\n\t\t\t\t\t<div class=\"panel-heading\">\n\t\t\t\t\t\tPERCEZIONE SENSORIALE\n\t\t\t\t\t</div>\n\t\t\t\t\t<div class=\"panel-body\">\n\t\t\t\t\t\t<div class=\"row\">\n\t\t\t\t\t\t\t<label class=\"col-sm-12\">Abilità a rispondere in modo corretto alla sensazione di disagio correlata alla\n\t\t\t\t\t\t\t\tposizione</label>\n\t\t\t\t\t\t\t<div class=\"col-sm-12\">\n\t\t\t\t\t\t\t\t<label class=\"ui-radio\" ng-click=\"formData.percezioneSensoriale={code:'op1a', score:1}\">\n\t\t\t\t\t\t\t\t\t<input name=\"\" type=\"radio\" value=\"op1a\" ng-model=\"formData.percezioneSensoriale.code\">\n\t\t\t\t\t\t\t\t\t<span>Completamente limitata</span>\n\t\t\t\t\t\t\t\t</label>\n\t\t\t\t\t\t\t\t<label class=\"ui-radio\" ng-click=\"formData.percezioneSensoriale={code:'op1b', score:2}\">\n\t\t\t\t\t\t\t\t\t<input name=\"\" type=\"radio\" value=\"op1b\" ng-model=\"formData.percezioneSensoriale.code\">\n\t\t\t\t\t\t\t\t\t<span>Molto limitata</span>\n\t\t\t\t\t\t\t\t</label>\n\t\t\t\t\t\t\t\t<label class=\"ui-radio\" ng-click=\"formData.percezioneSensoriale={code:'op1c',score:3}\">\n\t\t\t\t\t\t\t\t\t<input name=\"\" type=\"radio\" value=\"op1c\" ng-model=\"formData.percezioneSensoriale.code\">\n\t\t\t\t\t\t\t\t\t<span>Leggermente limitata</span>\n\t\t\t\t\t\t\t\t</label>\n\t\t\t\t\t\t\t\t<label class=\"ui-radio\" ng-click=\"formData.percezioneSensoriale={code:'op1d', score:4}\">\n\t\t\t\t\t\t\t\t\t<input name=\"\" type=\"radio\" value=\"op1d\" ng-model=\"formData.percezioneSensoriale.code\">\n\t\t\t\t\t\t\t\t\t<span>Non limitata</span>\n\t\t\t\t\t\t\t\t</label>\n\t\t\t\t\t\t\t\t<input class=\"form-control\" type=\"text\" summary=\"BRADENPSensoriale\" ng-model=\"formData.percezioneSensoriale.score\"\n\t\t\t\t\t\t\t\t ng-show=\"false\">\n\t\t\t\t\t\t\t</div>\n\n\t\t\t\t\t\t</div>\n\t\t\t\t\t</div>\n\t\t\t\t\t<div class=\"panel-footer\" align=\"justify\">\n\t\t\t\t\t\t<h5 style=\"margin-left:30px;\"><b>Legenda</b></h5>\n\t\t\t\t\t\t<ul>\n\t\t\t\t\t\t\t<li>\n\t\t\t\t\t\t\t\t<p><b>Completamente limitata:</b><span>&nbsp;Assenza di risposta (non geme, non si contrae o afferra) agli stimoli dolorosi\n\t\t\t\t\t\t\t\t\t\tdovuta alla riduzione dello stato di coscienza o a sedazione, OPPURE, limitata capacità di avvertire\n\t\t\t\t\t\t\t\t\t\tgli stimoli dolorosi su gran parte della superficie corporea</span></p>\n\t\t\t\t\t\t\t</li>\n\t\t\t\t\t\t\t<li>\n\t\t\t\t\t\t\t\t<p><b>Molto limitata:</b><span>&nbsp;Risponde solamente agli stimoli dolorosi. Non è in grado di comunicare il suo\n\t\t\t\t\t\t\t\t\t\tdisagio se nongemendo e agitandosi, OPPURE, ha un danno sensorila che limita la capacità di percepire il\n\t\t\t\t\t\t\t\t\t\tdolore e il disagio sul 50% della superficie corporea</span></p>\n\t\t\t\t\t\t\t</li>\n\t\t\t\t\t\t\t<li>\n\t\t\t\t\t\t\t\t<p><b>Leggermente limitata:</b><span>&nbsp;Risponde ai comandi verbali, ma non riesce a comunicare sempre il suo\n\t\t\t\t\t\t\t\t\t\tdisagio oppure necessita di essere routato, OPPURE, ha qualche limitazione sensoriale che limita la sua\n\t\t\t\t\t\t\t\t\t\tcapacità di percepire il dolore o il disagio in una o due estremità</span></p>\n\t\t\t\t\t\t\t</li>\n\t\t\t\t\t\t\t<li>\n\t\t\t\t\t\t\t\t<p><b>Non limitata:</b><span>&nbsp;Risponde ai comandi verbale. Non ha deficit sensoriali che limitano la\n\t\t\t\t\t\t\t\t\t\tcapacità di percepire il dolore o il disagio</span></p>\n\t\t\t\t\t\t\t</li>\n\t\t\t\t\t\t</ul>\n\t\t\t\t\t</div>\n\n\t\t\t\t</div>\n\t\t\t</div>\n\t\t\t<div class=\"col-xs-12 col-md-12 col-lg-6\">\n\t\t\t\t<div class=\"panel panel-primary\">\n\t\t\t\t\t<div class=\"panel-heading\">\n\t\t\t\t\t\tUMIDITA'\n\t\t\t\t\t</div>\n\t\t\t\t\t<div class=\"panel-body\">\n\t\t\t\t\t\t<div class=\"row\">\n\t\t\t\t\t\t\t<label class=\"col-sm-12\">Grado di esposizione della pelle all'umidità</label>\n\t\t\t\t\t\t\t<div class=\"col-sm-12\">\n\t\t\t\t\t\t\t\t<label class=\"ui-radio\" ng-click=\"formData.umidita={code:'op2a', score:1}\">\n\t\t\t\t\t\t\t\t\t<input name=\"\" type=\"radio\" value=\"op2a\" ng-model=\"formData.umidita.code\">\n\t\t\t\t\t\t\t\t\t<span>Costantemente bagnato</span>\n\t\t\t\t\t\t\t\t</label>\n\t\t\t\t\t\t\t\t<label class=\"ui-radio\" ng-click=\"formData.umidita={code:'op2b',score:2}\">\n\t\t\t\t\t\t\t\t\t<input name=\"\" type=\"radio\" value=\"op2b\" ng-model=\"formData.umidita.code\">\n\t\t\t\t\t\t\t\t\t<span>Spesso bagnato</span>\n\t\t\t\t\t\t\t\t</label>\n\t\t\t\t\t\t\t\t<label class=\"ui-radio\" ng-click=\"formData.umidita={code:'op2c',score:3}\">\n\t\t\t\t\t\t\t\t\t<input name=\"\" type=\"radio\" value=\"op2c\" ng-model=\"formData.umidita.code\">\n\t\t\t\t\t\t\t\t\t<span>Occasionalmente bagnato</span>\n\t\t\t\t\t\t\t\t</label>\n\t\t\t\t\t\t\t\t<label class=\"ui-radio\" ng-click=\"formData.umidita={code:'op2d', score:4}\">\n\t\t\t\t\t\t\t\t\t<input name=\"\" type=\"radio\" value=\"op2d\" ng-model=\"formData.umidita.code\">\n\t\t\t\t\t\t\t\t\t<span>Raramente bagnato</span>\n\t\t\t\t\t\t\t\t</label>\n\t\t\t\t\t\t\t\t<input class=\"form-control\" type=\"text\" summary=\"BRADENUmidita\" ng-model=\"formData.umidita.score\" ng-show=\"false\">\n\t\t\t\t\t\t\t</div>\n\n\t\t\t\t\t\t</div>\n\t\t\t\t\t</div>\n\t\t\t\t\t<div class=\"panel-footer\" align=\"justify\">\n\t\t\t\t\t\t<h5 style=\"margin-left:30px;\"><b>Legenda</b></h5>\n\t\t\t\t\t\t<ul>\n\t\t\t\t\t\t\t<li>\n\t\t\t\t\t\t\t\t<p><b>Costantemente bagnato:</b><span>&nbsp;La cute è costantemente umida a causa della sudorazione, delle urine, etc.\n\t\t\t\t\t\t\t\t\t\tL'umidità viene riscontrata ogni volta che il soggetto viene mosso o ruotato</span></p>\n\t\t\t\t\t\t\t</li>\n\t\t\t\t\t\t\t<li>\n\t\t\t\t\t\t\t\t<p><b>Spesso bagnato:</b><span>&nbsp;La cute è spesso, ma non sempre umida. Il pannolone o la biancheria viene cambiata\n\t\t\t\t\t\t\t\t\t\talmeno una volta per turno</span></p>\n\t\t\t\t\t\t\t</li>\n\t\t\t\t\t\t\t<li>\n\t\t\t\t\t\t\t\t<p><b>Occasionalmente bagnato:</b><span>&nbsp;La cute è occasionalmente umida, è richiesto un cambio della biancheria\n\t\t\t\t\t\t\t\t\t\tcirca una volta al giorno</span></p>\n\t\t\t\t\t\t\t</li>\n\t\t\t\t\t\t\t<li>\n\t\t\t\t\t\t\t\t<p><b>Raramente bagnato:</b><span>&nbsp;La cute è normalemente asciutta, la biancheria viene cambiata secondo gli\n\t\t\t\t\t\t\t\t\t\tintervalli abituali in uso.</span></p>\n\t\t\t\t\t\t\t</li>\n\t\t\t\t\t\t</ul>\n\t\t\t\t\t</div>\n\n\t\t\t\t</div>\n\t\t\t</div>\n\t\t</div>\n\t\t<div class=\"row\">\n\t\t\t<div class=\"col-xs-12 col-md-12 col-lg-6\">\n\t\t\t\t<div class=\"panel panel-primary\">\n\t\t\t\t\t<div class=\"panel-heading\">\n\t\t\t\t\t\tATTIVITA'\n\t\t\t\t\t</div>\n\t\t\t\t\t<div class=\"panel-body\">\n\t\t\t\t\t\t<div class=\"row\">\n\t\t\t\t\t\t\t<label class=\"col-sm-12\">Grado di attività fisica</label>\n\t\t\t\t\t\t\t<div class=\"col-sm-12\">\n\t\t\t\t\t\t\t\t<label class=\"ui-radio\" ng-click=\"formData.attivita={code:'op3a', score:1}\">\n\t\t\t\t\t\t\t\t\t<input name=\"\" type=\"radio\" value=\"op3a\" ng-model=\"formData.attivita.code\">\n\t\t\t\t\t\t\t\t\t<span>Completamente allettato</span>\n\t\t\t\t\t\t\t\t</label>\n\t\t\t\t\t\t\t\t<label class=\"ui-radio\" ng-click=\"formData.attivita={code:'op3b',score:2}\">\n\t\t\t\t\t\t\t\t\t<input name=\"\" type=\"radio\" value=\"op3b\" ng-model=\"formData.attivita.code\">\n\t\t\t\t\t\t\t\t\t<span>In poltrona</span>\n\t\t\t\t\t\t\t\t</label>\n\t\t\t\t\t\t\t\t<label class=\"ui-radio\" ng-click=\"formData.attivita={code:'op3c', score:3}\">\n\t\t\t\t\t\t\t\t\t<input name=\"\" type=\"radio\" value=\"op3c\" ng-model=\"formData.attivita.code\">\n\t\t\t\t\t\t\t\t\t<span>Cammina occasionalmente</span>\n\t\t\t\t\t\t\t\t</label>\n\t\t\t\t\t\t\t\t<label class=\"ui-radio\" ng-click=\"formData.attivita={code:'op3d',score:4}\">\n\t\t\t\t\t\t\t\t\t<input name=\"\" type=\"radio\" value=\"op3d\" ng-model=\"formData.attivita.code\">\n\t\t\t\t\t\t\t\t\t<span>Cammina di frequente</span>\n\t\t\t\t\t\t\t\t</label>\n\t\t\t\t\t\t\t\t<input class=\"form-control\" type=\"text\" summary=\"BRADENAttivita\" ng-model=\"formData.attivita.score\" ng-show=\"false\">\n\t\t\t\t\t\t\t</div>\n\n\t\t\t\t\t\t</div>\n\t\t\t\t\t</div>\n\t\t\t\t\t<div class=\"panel-footer\" align=\"justify\">\n\t\t\t\t\t\t<h5 style=\"margin-left:30px;\"><b>Legenda</b></h5>\n\t\t\t\t\t\t<ul>\n\t\t\t\t\t\t\t<li>\n\t\t\t\t\t\t\t\t<p><b>Completamente allettato:</b><span>&nbsp;Confinato a letto</span></p>\n\t\t\t\t\t\t\t</li>\n\t\t\t\t\t\t\t<li>\n\t\t\t\t\t\t\t\t<p><b>In poltrona:</b><span>&nbsp;Capacità di camminare molto limitata o assente. Non riesce a spostare il suo peso\n\t\t\t\t\t\t\t\t\t\te/o deve essere assistito in poltrona o sulla carrozzella</span></p>\n\t\t\t\t\t\t\t</li>\n\t\t\t\t\t\t\t<li>\n\t\t\t\t\t\t\t\t<p><b>Cammina Occasionalmente:</b><span>&nbsp;Cammina occasionalmente durante la giornata, ma per distanze molto\n\t\t\t\t\t\t\t\t\t\tbrevi, con o senza aiuto. Passa la maggior parte del tempo a letto o in poltrona</span></p>\n\t\t\t\t\t\t\t</li>\n\t\t\t\t\t\t\t<li>\n\t\t\t\t\t\t\t\t<p><b>Cammina di Frequente:</b><span>&nbsp;Cammina al di fuori della sua stanza almento due volte al giorno e nella\n\t\t\t\t\t\t\t\t\t\tstanza almeno ogni due ore durante le ore diurne</span></p>\n\t\t\t\t\t\t\t</li>\n\t\t\t\t\t\t</ul>\n\t\t\t\t\t</div>\n\n\t\t\t\t</div>\n\t\t\t</div>\n\t\t\t<div class=\"col-xs-12 col-md-12 col-lg-6\">\n\t\t\t\t<div class=\"panel panel-primary\">\n\t\t\t\t\t<div class=\"panel-heading\">\n\t\t\t\t\t\tMOBILITA'\n\t\t\t\t\t</div>\n\t\t\t\t\t<div class=\"panel-body\">\n\t\t\t\t\t\t<div class=\"row\">\n\t\t\t\t\t\t\t<label class=\"col-sm-12\">Capacità di cambiare e di controllare le posizioni del corpo</label>\n\t\t\t\t\t\t\t<div class=\"col-sm-12\">\n\t\t\t\t\t\t\t\t<label class=\"ui-radio\" ng-click=\"formData.mobilita={code:'op4a', score:1}\">\n\t\t\t\t\t\t\t\t\t<input name=\"\" type=\"radio\" value=\"op4a\" ng-model=\"formData.mobilita.code\">\n\t\t\t\t\t\t\t\t\t<span>Completamente immobile</span>\n\t\t\t\t\t\t\t\t</label>\n\t\t\t\t\t\t\t\t<label class=\"ui-radio\" ng-click=\"formData.mobilita={code:'op4b', score:2}\">\n\t\t\t\t\t\t\t\t\t<input name=\"\" type=\"radio\" value=\"op4b\" ng-model=\"formData.mobilita.code\">\n\t\t\t\t\t\t\t\t\t<span>Molto limitata</span>\n\t\t\t\t\t\t\t\t</label>\n\t\t\t\t\t\t\t\t<label class=\"ui-radio\" ng-click=\"formData.mobilita={code:'op4c', score:3}\">\n\t\t\t\t\t\t\t\t\t<input name=\"\" type=\"radio\" value=\"op4c\" ng-model=\"formData.mobilita.code\">\n\t\t\t\t\t\t\t\t\t<span>Parzialmente limitata</span>\n\t\t\t\t\t\t\t\t</label>\n\t\t\t\t\t\t\t\t<label class=\"ui-radio\" ng-click=\"formData.mobilita={code:'op4d', score:4}\">\n\t\t\t\t\t\t\t\t\t<input name=\"\" type=\"radio\" value=\"op4d\" ng-model=\"formData.mobilita.code\">\n\t\t\t\t\t\t\t\t\t<span>Limitazioni assenti</span>\n\t\t\t\t\t\t\t\t</label>\n\t\t\t\t\t\t\t\t<input class=\"form-control\" type=\"text\" summary=\"BRADENmobilita\" ng-model=\"formData.mobilita.score\" ng-show=\"false\">\n\t\t\t\t\t\t\t</div>\n\t\t\t\t\t\t</div>\n\t\t\t\t\t</div>\n\t\t\t\t\t<div class=\"panel-footer\" align=\"justify\">\n\t\t\t\t\t\t<h5 style=\"margin-left:30px;\"><b>Legenda</b></h5>\n\t\t\t\t\t\t<ul>\n\t\t\t\t\t\t\t<li>\n\t\t\t\t\t\t\t\t<p><b>Completamente immobile:</b><span>&nbsp;Non riesce a produrre neppure piccoli movimenti del corpo e delle\n\t\t\t\t\t\t\t\t\t\testremità senza assistenza</span></p>\n\t\t\t\t\t\t\t</li>\n\t\t\t\t\t\t\t<li>\n\t\t\t\t\t\t\t\t<p><b>Molto limitata:</b><span>&nbsp;Riesce occasionalmente a fare piccoli movimenti corporei o delle estremità, ma\n\t\t\t\t\t\t\t\t\t\tnon riesce a realizzare frequenti o significativi movimenti in modo indipendente</span></p>\n\t\t\t\t\t\t\t</li>\n\t\t\t\t\t\t\t<li>\n\t\t\t\t\t\t\t\t<p><b>Parzialmente limitata:</b><span>&nbsp;Cambia frequentemente la posizione con minimi spostamenti del corpo</span></p>\n\t\t\t\t\t\t\t</li>\n\t\t\t\t\t\t\t<li>\n\t\t\t\t\t\t\t\t<p><b>Limitazioni assenti:</b><span>&nbsp;Si sposta frequentemente e senza assistenza</span></p>\n\t\t\t\t\t\t\t</li>\n\t\t\t\t\t\t</ul>\n\t\t\t\t\t</div>\n\n\t\t\t\t</div>\n\t\t\t</div>\n\t\t</div>\n\t\t<div class=\"row\">\n\t\t\t<div class=\"col-xs-12 col-md-12 col-lg-6\">\n\t\t\t\t<div class=\"panel panel-primary\">\n\t\t\t\t\t<div class=\"panel-heading\">\n\t\t\t\t\t\tNUTRIZIONE\n\t\t\t\t\t</div>\n\t\t\t\t\t<div class=\"panel-body\">\n\t\t\t\t\t\t<div class=\"row\">\n\t\t\t\t\t\t\t<label class=\"col-sm-12\">Assunziona usuale di cibo</label>\n\t\t\t\t\t\t\t<div class=\"col-sm-12\">\n\t\t\t\t\t\t\t\t<label class=\"ui-radio\" ng-click=\"formData.nutrizione={code:'op5a', score:1}\">\n\t\t\t\t\t\t\t\t\t<input name=\"\" type=\"radio\" value=\"op5a\" ng-model=\"formData.nutrizione.code\">\n\t\t\t\t\t\t\t\t\t<span>Molto povera</span>\n\t\t\t\t\t\t\t\t</label>\n\t\t\t\t\t\t\t\t<label class=\"ui-radio\" ng-click=\"formData.nutrizione={code:'op5b', score:2}\">\n\t\t\t\t\t\t\t\t\t<input name=\"\" type=\"radio\" value=\"op5b\" ng-model=\"formData.nutrizione.code\">\n\t\t\t\t\t\t\t\t\t<span>Probabilmente inadeguata</span>\n\t\t\t\t\t\t\t\t</label>\n\t\t\t\t\t\t\t\t<label class=\"ui-radio\" ng-click=\"formData.nutrizione={code:'op5c', score:3}\">\n\t\t\t\t\t\t\t\t\t<input name=\"\" type=\"radio\" value=\"op5c\" ng-model=\"formData.nutrizione.code\">\n\t\t\t\t\t\t\t\t\t<span>Adeguata</span>\n\t\t\t\t\t\t\t\t</label>\n\t\t\t\t\t\t\t\t<label class=\"ui-radio\" ng-click=\"formData.nutrizione={code:'op5d', score:4}\">\n\t\t\t\t\t\t\t\t\t<input name=\"\" type=\"radio\" value=\"op5d\" ng-model=\"formData.nutrizione.code\">\n\t\t\t\t\t\t\t\t\t<span>Eccellente</span>\n\t\t\t\t\t\t\t\t</label>\n\t\t\t\t\t\t\t\t<input class=\"form-control\" type=\"text\" summary=\"BRADENNutrizione\" ng-model=\"formData.nutrizione.score\" ng-show=\"false\">\n\t\t\t\t\t\t\t</div>\n\t\t\t\t\t\t</div>\n\t\t\t\t\t</div>\n\t\t\t\t\t<div class=\"panel-footer\" align=\"justify\">\n\t\t\t\t\t\t<h5 style=\"margin-left:30px;\"><b>Legenda</b></h5>\n\t\t\t\t\t\t<ul>\n\t\t\t\t\t\t\t<li>\n\t\t\t\t\t\t\t\t<p><b>Molto povera:</b><span>&nbsp;Non mangia mai un pasto completo. Raramente mangia pià di 1/3 di qualsiasi cibo\n\t\t\t\t\t\t\t\t\t\tofferto. Duo o meno porzioni di proteine al giorno. Assume pochi liquidi e nessun integratore, OPPURE, è a\n\t\t\t\t\t\t\t\t\t\tdigiuno o sostenuto solamente con fleboclisi o a dieta esclusivamente idrica per più di 5 giorni</span></p>\n\t\t\t\t\t\t\t</li>\n\t\t\t\t\t\t\t<li>\n\t\t\t\t\t\t\t\t<p><b>Probabilmente inadeguata:</b><span>&nbsp;Raramente mangia un pasto completo, generalmente mangia la metà dei\n\t\t\t\t\t\t\t\t\t\tcibi offerti. Le proteine assunte includono 3 porzioni di carne o latticini al giorno, occasionalmente\n\t\t\t\t\t\t\t\t\t\tintegratori alimentari, OPPURE, Riceve una quantità scarsa rispetto a quanto prevista come dieta liquida\n\t\t\t\t\t\t\t\t\t\tenterale ( via SNG o PEG )</span></p>\n\t\t\t\t\t\t\t</li>\n\t\t\t\t\t\t\t<li>\n\t\t\t\t\t\t\t\t<p><b>Adeguata:</b><span>&nbsp;Mangia più della metà dei pasti. 4 o più porzioni di proteine al giorno. Assume\n\t\t\t\t\t\t\t\t\t\tnormalmente integratori, OPPURE, si alimenta artificialmente (via SNG/ PEG), assumendo il quantitativo\n\t\t\t\t\t\t\t\t\t\tnutrizionale necessario</span></p>\n\t\t\t\t\t\t\t</li>\n\t\t\t\t\t\t\t<li>\n\t\t\t\t\t\t\t\t<p><b>Eccellente:</b><span>&nbsp;Mangia la maggio parte del cibo. Non rifiura mai un pasto. talvolta mangia tra i\n\t\t\t\t\t\t\t\t\t\tpasti, Non ha necessità di integratori</span></p>\n\t\t\t\t\t\t\t</li>\n\t\t\t\t\t\t</ul>\n\t\t\t\t\t</div>\n\n\t\t\t\t</div>\n\t\t\t</div>\n\t\t\t<div class=\"col-xs-12 col-md-12 col-lg-6\">\n\t\t\t\t<div class=\"panel panel-primary\">\n\t\t\t\t\t<div class=\"panel-heading\">\n\t\t\t\t\t\tATTRITO E FRIZIONE\n\t\t\t\t\t</div>\n\t\t\t\t\t<div class=\"panel-body\">\n\t\t\t\t\t\t<div class=\"row\">\n\t\t\t\t\t\t\t<label class=\"col-sm-12\">Attrito e Frizione</label>\n\t\t\t\t\t\t\t<div class=\"col-sm-12\">\n\t\t\t\t\t\t\t\t<label class=\"ui-radio\" ng-click=\"formData.attritoFrizione={code:'op6a', score:1}\">\n\t\t\t\t\t\t\t\t\t<input name=\"\" type=\"radio\" value=\"op6a\" ng-model=\"formData.attritoFrizione.code\">\n\t\t\t\t\t\t\t\t\t<span>Problema presente</span>\n\t\t\t\t\t\t\t\t</label>\n\t\t\t\t\t\t\t\t<label class=\"ui-radio\" ng-click=\"formData.attritoFrizione={code:'op6b', score:2}\">\n\t\t\t\t\t\t\t\t\t<input name=\"\" type=\"radio\" value=\"op6b\" ng-model=\"formData.attritoFrizione.code\">\n\t\t\t\t\t\t\t\t\t<span>Problema potenziale</span>\n\t\t\t\t\t\t\t\t</label>\n\t\t\t\t\t\t\t\t<label class=\"ui-radio\" ng-click=\"formData.attritoFrizione={code:'op6c', score:3}\">\n\t\t\t\t\t\t\t\t\t<input name=\"\" type=\"radio\" value=\"op6c\" ng-model=\"formData.attritoFrizione.code\">\n\t\t\t\t\t\t\t\t\t<span>Senza problemi apparenti</span>\n\t\t\t\t\t\t\t\t</label>\n\t\t\t\t\t\t\t\t<input class=\"form-control\" type=\"text\" summary=\"BRADENAttFrizione\" ng-model=\"formData.attritoFrizione.score\"\n\t\t\t\t\t\t\t\t ng-show=\"false\">\n\t\t\t\t\t\t\t</div>\n\t\t\t\t\t\t</div>\n\t\t\t\t\t</div>\n\t\t\t\t\t<div class=\"panel-footer\" align=\"justify\">\n\t\t\t\t\t\t<h5 style=\"margin-left:30px;\"><b>Legenda</b></h5>\n\t\t\t\t\t\t<ul>\n\t\t\t\t\t\t\t<li>\n\t\t\t\t\t\t\t\t<p><b>Problema presente:</b><span>&nbsp;Richiede da moderata a completa assistenza nei movimenti. Scivola di frequente nel\n\t\t\t\t\t\t\t\t\t\tletto o nella poltrona. Spesso richiede riposizionamentocon assistenza. Sono presenti spasticità,\n\t\t\t\t\t\t\t\t\t\tcontratture, agitazione, che causanocostante attrito control il piano del letto o della poltrona</span></p>\n\t\t\t\t\t\t\t</li>\n\t\t\t\t\t\t\t<li>\n\t\t\t\t\t\t\t\t<p><b>Problema Potenziale:</b><span>&nbsp;Si muove poco e necessita di una minima assistenza. Durante lo spostamentom\n\t\t\t\t\t\t\t\t\t\tla cute fa attrito con le lenzuola o con il piano della poltrona, occasionalmente può slittare</span></p>\n\t\t\t\t\t\t\t</li>\n\t\t\t\t\t\t\t<li>\n\t\t\t\t\t\t\t\t<p><b>Senza problemi apparenti:</b><span>&nbsp;Si sposta nel letto e sulla sedia in modo autonomo ed ha sufficiente\n\t\t\t\t\t\t\t\t\t\tforza muscolare per sollevarsi completamente durante i movimenti</span></p>\n\t\t\t\t\t\t\t</li>\n\t\t\t\t\t\t</ul>\n\t\t\t\t\t</div>\n\n\t\t\t\t</div>\n\t\t\t</div>\n\t\t</div>\n\n\t\t<div class=\"row\">\n\t\t\t<div class=\"col-xs-12 col-sm-12 col-md-12\">\n\t\t\t\t<div class=\"panel panel-primary\">\n\t\t\t\t\t<div class=\"panel-heading\">\n\t\t\t\t\t\tTOTALE\n\t\t\t\t\t</div>\n\t\t\t\t\t<div class=\"panel-body\">\n\t\t\t\t\t\t<div class=\"row\">\n\t\t\t\t\t\t\t<label class=\"col-xs-12 col-md-2 col-lg-2\">Punteggio Totale</label>\n\t\t\t\t\t\t\t<div class=\"col-xs-6 col-md-3 col-lg-3\">\n\t\t\t\t\t\t\t\t<input class=\"form-control\" type=\"text\" concept=\"scoreBRADENTotal\" summary ng-model=\"formData.scoreTotal\"\n\t\t\t\t\t\t\t\t readonly>\n\t\t\t\t\t\t\t</div>\n\t\t\t\t\t\t</div>\n\t\t\t\t\t</div>\n\t\t\t\t\t<div class=\"panel-footer\">\n\t\t\t\t\t\t<label class=\"control-label\">Legenda</label>\n\t\t\t\t\t\t<p>Punteggio &#62 16 - Paziente non a rischio </p>\n\t\t\t\t\t\t<p>Punteggio da 13 a 16 - Paziente a rischio </p>\n\t\t\t\t\t\t<p>Punteggio &#60 13 - Paziente ad alto rischio</p>\n\t\t\t\t\t</div>\n\t\t\t\t</div>\n\t\t\t</div>\n\t\t</div>\n\t</div>\n</section>",
  "javascript": "\n\n\nvar calcoloTotaleScore = function (){\n  var somma=null;\n  if(formData.percezioneSensoriale != undefined && formData.percezioneSensoriale.score > 0)\n  somma +=formData.percezioneSensoriale.score;\n  if(formData.umidita != undefined && formData.umidita.score > 0)\n  somma +=formData.umidita.score;\n  if(formData.attivita != undefined && formData.attivita.score > 0)\n  somma +=formData.attivita.score;\n  if(formData.movilita != undefined && formData.movilita.score > 0)\n  somma +=formData.mobilita.score;\n  if(formData.nutrizione != undefined && formData.nutrizione.score > 0)\n  somma +=formData.nutrizione.score;\n  if(formData.attritoFrizione != undefined && formData.attritoFrizione.score > 0)\n  somma +=formData.attritoFrizione.score;\n \n  formData.scoreTotal=somma;\n};\nregisterFunction(\"calcoloTotaleScore\",calcoloTotaleScore);\n\nvar selectRadio = function(event){\n  if (formData != changeJson){\n    calcoloTotaleScore();\n  }\n  var changeJson = angular.copy(formData);\n};\nregisterFunction(\"selectRadio\",selectRadio);\n\n\n\n\n",
  "css": "",
  "version": 1,
  "status": "DRAFT",
  "bundleValues": {
    "it_IT": {
      "BRADENAttFrizione": "",
      "BRADENmobilita": "",
      "BRADENAttivita": "",
      "BRADENNutrizione": "",
      "BRADENPSensoriale": "",
      "BRADENCommento": "",
      "BRADENUmidita": ""
    },
    "en_GB": {
      "BRADENAttFrizione": "",
      "BRADENmobilita": "",
      "BRADENAttivita": "",
      "BRADENNutrizione": "",
      "BRADENPSensoriale": "",
      "BRADENCommento": "",
      "BRADENUmidita": ""
    },
    "es_ES": {
      "BRADENAttFrizione": "",
      "BRADENmobilita": "",
      "BRADENAttivita": "",
      "BRADENNutrizione": "",
      "BRADENPSensoriale": "",
      "BRADENCommento": "",
      "BRADENUmidita": ""
    },
    "de_DE": {
      "BRADENAttFrizione": "",
      "BRADENmobilita": "",
      "BRADENAttivita": "",
      "BRADENNutrizione": "",
      "BRADENPSensoriale": "",
      "BRADENCommento": "",
      "BRADENUmidita": ""
    }
  },
  "templateFileName": null,
  "templateApplications": {},
  "repositoryEnabled": null,
  "signatureEnabled": null,
  "signatureNotMandatory": null,
  "sendTxtEnabled": null,
  "sendPrivacyEnabled": null,
  "cda2Enabled": null,
  "cda2Xlts": null,
  "cancellableEnabled": null,
  "saveAsDraftWhenInvalid": null
}]
